swatchbook/__init__.py
swatchbook/apps.py
swatchbook/blocks.py
swatchbook/colour_stylesheet.py
swatchbook/font_stylesheet.py
swatchbook/model_porter.py
swatchbook/models.py
swatchbook/utilities.py
swatchbook/variable_stylesheet.py
swatchbook/wagtail_hooks.py
swatchbook/widgets.py
swatchbook/migrations/0001_initial.py
swatchbook/migrations/0002_add_attachment_roles.py
swatchbook/migrations/__init__.py
swatchbook/static/swatchbook/css/swatchbook.css
swatchbook/static/swatchbook/css/swatchbook.css.map
swatchbook/static/swatchbook/js/swatchbook.js
swatchbook/static/swatchbook/js/swatchbook.js.map
swatchbook/templates/swatchbook/tags/support.html
swatchbook/templatetags/__init__.py
swatchbook/templatetags/swatchbook_tags.py
swatchbook-4.1.0.dist-info/AUTHORS.txt
swatchbook-4.1.0.dist-info/LICENSE.txt
swatchbook-4.1.0.dist-info/METADATA
swatchbook-4.1.0.dist-info/WHEEL
swatchbook-4.1.0.dist-info/top_level.txt
swatchbook-4.1.0.dist-info/RECORD
